pass_collaborate/__init__.py
pass_collaborate/adapters.py
pass_collaborate/assets/access.bash
pass_collaborate/assets/auth.yaml
pass_collaborate/assets/group.bash
pass_collaborate/assets/user.bash
pass_collaborate/entrypoints/__init__.py
pass_collaborate/entrypoints/cli.py
pass_collaborate/entrypoints/group.py
pass_collaborate/entrypoints/user.py
pass_collaborate/exceptions.py
pass_collaborate/model/__init__.py
pass_collaborate/model/auth.py
pass_collaborate/model/key.py
pass_collaborate/model/pass_.py
pass_collaborate/py.typed
pass_collaborate/services.py
pass_collaborate/version.py
pass_collaborate/views.py
pass_collaborate-0.2.2.dist-info/entry_points.txt
pass_collaborate-0.2.2.dist-info/WHEEL
pass_collaborate-0.2.2.dist-info/METADATA
pass_collaborate-0.2.2.dist-info/licenses/LICENSE
pass_collaborate-0.2.2.dist-info/RECORD
