Metadata-Version: 2.1
Name: pass-collaborate
Version: 0.2.2
Summary: A pass extension that helps collectives manage the access to their passwords
License: GPL-3.0-only
Author-email: Lyz <lyz-code-security-advisories@riseup.net>
Requires-Python: >=3.9
Classifier: Development Status :: 2 - Pre-Alpha
Classifier: Intended Audience :: Developers
Classifier: License :: OSI Approved :: GNU General Public License v3 (GPLv3)
Classifier: Natural Language :: English
Classifier: Operating System :: POSIX
Classifier: Operating System :: Unix
Classifier: Programming Language :: Python
Classifier: Programming Language :: Python :: 3
Classifier: Programming Language :: Python :: 3.10
Classifier: Programming Language :: Python :: 3.7
Classifier: Programming Language :: Python :: 3.8
Classifier: Programming Language :: Python :: 3.9
Classifier: Topic :: Utilities
Requires-Dist: click>=8.1.3
Requires-Dist: goodconf[yaml]>=2.0.1
Requires-Dist: pydantic[email]<2.0.0,>=1.10.2
Requires-Dist: python-gnupg>=0.5.0
Requires-Dist: rich>=12.6.0
Requires-Dist: ruyaml>=0.91.0
Requires-Dist: typer>=0.7.0
Project-URL: Issues, https://github.com/lyz-code/pass-collaborate/issues
Project-URL: documentation, https://lyz-code.github.io/pass-collaborate
Project-URL: homepage, https://github.com/lyz-code/pass-collaborate
